bessie/__init__.py
bessie/base.py
bessie/endpoints.py
bessie-0.0.1.dist-info/DESCRIPTION.rst
bessie-0.0.1.dist-info/METADATA
bessie-0.0.1.dist-info/RECORD
bessie-0.0.1.dist-info/WHEEL
bessie-0.0.1.dist-info/metadata.json
bessie-0.0.1.dist-info/top_level.txt
tests/__init__.py
tests/test_base.py
tests/test_endpoints.py
