Metadata-Version: 2.0
Name: bessie
Version: 0.0.1
Summary: Bessie - Base API Client
Home-page: https://github.com/andymitchhank/bessie
Author: Andrew Henry
Author-email: andymitchhank@users.noreply.github.com
License: MIT
Platform: UNKNOWN
Classifier: Development Status :: 3 - Alpha
Classifier: Intended Audience :: Developers
Classifier: License :: OSI Approved :: MIT License
Classifier: Natural Language :: English
Classifier: Operating System :: OS Independent
Classifier: Programming Language :: Python :: 3.6
Classifier: Programming Language :: Python :: Implementation :: CPython
Classifier: Programming Language :: Python :: Implementation :: PyPy
Requires-Dist: requests
